{"nodesLookup":{"107421":{"rank":1.0416825539880061,"label":"SequenceLock","id":107421,"variant":0,"Pos":""},"11694":{"rank":1.1531668230239995,"label":"blockIndex","id":11694,"variant":0,"Pos":""},"147784":{"rank":1.0416825539880061,"label":"IndexManager","id":147784,"variant":0,"Pos":""},"148564":{"rank":1.0416825539880061,"label":"Config","id":148564,"variant":0,"Pos":""},"155041":{"rank":1.0416825539880061,"label":"MedianTimeSource","id":155041,"variant":0,"Pos":""},"155654":{"rank":1.0416825539880061,"label":"int64Sorter","id":155654,"variant":0,"Pos":""},"156512":{"rank":1.0416825539880061,"label":"medianTime","id":156512,"variant":0,"Pos":""},"161838":{"rank":1.0416825539880061,"label":"txValidateItem","id":161838,"variant":0,"Pos":""},"162176":{"rank":1.6252383098200978,"label":"txValidator","id":162176,"variant":0,"Pos":""},"181526":{"rank":1.0416825539880061,"label":"ThresholdState","id":181526,"variant":0,"Pos":""},"183402":{"rank":1.0416825539880061,"label":"thresholdConditionChecker","id":183402,"variant":0,"Pos":""},"184480":{"rank":1.9335567062759489,"label":"thresholdStateCache","id":184480,"variant":0,"Pos":""},"194785":{"rank":1.0416825539880061,"label":"errNotInMainChain","id":194785,"variant":0,"Pos":""},"195197":{"rank":1.0416825539880061,"label":"errDeserialize","id":195197,"variant":0,"Pos":""},"200335":{"rank":1.0416825539880061,"label":"spentTxOut","id":200335,"variant":0,"Pos":""},"229867":{"rank":1.0416825539880061,"label":"bestChainState","id":229867,"variant":0,"Pos":""},"242549":{"rank":1.3751429858920579,"label":"utxoOutput","id":242549,"variant":0,"Pos":""},"243383":{"rank":2.125428957676176,"label":"UtxoEntry","id":243383,"variant":0,"Pos":""},"247950":{"rank":1.3751429858920579,"label":"UtxoViewpoint","id":247950,"variant":0,"Pos":""},"311978":{"rank":1.0416825539880061,"label":"timeSorter","id":311978,"variant":0,"Pos":""},"323005":{"rank":1.0974246885060028,"label":"bitConditionChecker","id":323005,"variant":0,"Pos":""},"325922":{"rank":1.0416825539880061,"label":"deploymentChecker","id":325922,"variant":0,"Pos":""},"37138":{"rank":1.0416825539880061,"label":"NotificationType","id":37138,"variant":0,"Pos":""},"37281":{"rank":1.0416825539880061,"label":"NotificationCallback","id":37281,"variant":0,"Pos":""},"38748":{"rank":1.0416825539880061,"label":"Notification","id":38748,"variant":0,"Pos":""},"3972":{"rank":1.0416825539880061,"label":"blockStatus","id":3972,"variant":0,"Pos":""},"5667":{"rank":2.4352359169379163,"label":"blockNode","id":5667,"variant":0,"Pos":""},"61052":{"rank":1.0416825539880061,"label":"BehaviorFlags","id":61052,"variant":0,"Pos":""},"69640":{"rank":1.0416825539880061,"label":"DeploymentError","id":69640,"variant":0,"Pos":""},"70031":{"rank":1.0416825539880061,"label":"AssertError","id":70031,"variant":0,"Pos":""},"70281":{"rank":1.0416825539880061,"label":"ErrorCode","id":70281,"variant":0,"Pos":""},"80122":{"rank":1.0416825539880061,"label":"RuleError","id":80122,"variant":0,"Pos":""},"81948":{"rank":6,"label":"chainView","id":81948,"variant":0,"Pos":""},"842456547840":{"rank":1,"label":"blockchain","id":842456547840,"variant":4,"Pos":""},"842533187232":{"rank":1.0974246885060028,"label":"newBlockNode","id":842533187232,"variant":8,"Pos":""},"842533187456":{"rank":1.0974246885060028,"label":"newBlockIndex","id":842533187456,"variant":8,"Pos":""},"842533188656":{"rank":1.0416825539880061,"label":"New","id":842533188656,"variant":2,"Pos":""},"842533188672":{"rank":1.0974246885060028,"label":"newChainView","id":842533188672,"variant":2,"Pos":""},"842533190176":{"rank":1.0416825539880061,"label":"NewMedianTime","id":842533190176,"variant":2,"Pos":""},"95965":{"rank":1.0416825539880061,"label":"BlockLocator","id":95965,"variant":0,"Pos":""},"96166":{"rank":1.0416825539880061,"label":"orphanBlock","id":96166,"variant":0,"Pos":""},"96762":{"rank":1.0416825539880061,"label":"BestState","id":96762,"variant":0,"Pos":""},"97978":{"rank":1.7663303027219597,"label":"BlockChain","id":97978,"variant":0,"Pos":""}},"nodes":[{"rank":1.0416825539880061,"label":"MedianTimeSource","id":155041,"variant":0,"Pos":""},{"rank":1.0416825539880061,"label":"ErrorCode","id":70281,"variant":0,"Pos":""},{"rank":1.0416825539880061,"label":"int64Sorter","id":155654,"variant":0,"Pos":""},{"rank":1.0416825539880061,"label":"SequenceLock","id":107421,"variant":0,"Pos":""},{"rank":1.0416825539880061,"label":"BlockLocator","id":95965,"variant":0,"Pos":""},{"rank":1.0416825539880061,"label":"txValidateItem","id":161838,"variant":0,"Pos":""},{"rank":1.0416825539880061,"label":"AssertError","id":70031,"variant":0,"Pos":""},{"rank":1.0416825539880061,"label":"IndexManager","id":147784,"variant":0,"Pos":""},{"rank":2.125428957676176,"label":"UtxoEntry","id":243383,"variant":0,"Pos":""},{"rank":1.0416825539880061,"label":"thresholdConditionChecker","id":183402,"variant":0,"Pos":""},{"rank":1.0416825539880061,"label":"RuleError","id":80122,"variant":0,"Pos":""},{"rank":1.0416825539880061,"label":"errNotInMainChain","id":194785,"variant":0,"Pos":""},{"rank":1.0416825539880061,"label":"BestState","id":96762,"variant":0,"Pos":""},{"rank":1.0416825539880061,"label":"orphanBlock","id":96166,"variant":0,"Pos":""},{"rank":1.6252383098200978,"label":"txValidator","id":162176,"variant":0,"Pos":""},{"rank":1.7663303027219597,"label":"BlockChain","id":97978,"variant":0,"Pos":""},{"rank":1,"label":"blockchain","id":842456547840,"variant":4,"Pos":""},{"rank":1.0416825539880061,"label":"NewMedianTime","id":842533190176,"variant":2,"Pos":""},{"rank":1.0416825539880061,"label":"DeploymentError","id":69640,"variant":0,"Pos":""},{"rank":1.0974246885060028,"label":"newBlockIndex","id":842533187456,"variant":8,"Pos":""},{"rank":1.3751429858920579,"label":"utxoOutput","id":242549,"variant":0,"Pos":""},{"rank":1.0974246885060028,"label":"newChainView","id":842533188672,"variant":2,"Pos":""},{"rank":1.3751429858920579,"label":"UtxoViewpoint","id":247950,"variant":0,"Pos":""},{"rank":1.0416825539880061,"label":"BehaviorFlags","id":61052,"variant":0,"Pos":""},{"rank":1.0416825539880061,"label":"timeSorter","id":311978,"variant":0,"Pos":""},{"rank":1.0416825539880061,"label":"blockStatus","id":3972,"variant":0,"Pos":""},{"rank":1.0416825539880061,"label":"spentTxOut","id":200335,"variant":0,"Pos":""},{"rank":1.0416825539880061,"label":"ThresholdState","id":181526,"variant":0,"Pos":""},{"rank":1.0416825539880061,"label":"deploymentChecker","id":325922,"variant":0,"Pos":""},{"rank":1.0974246885060028,"label":"bitConditionChecker","id":323005,"variant":0,"Pos":""},{"rank":1.0974246885060028,"label":"newBlockNode","id":842533187232,"variant":8,"Pos":""},{"rank":1.0416825539880061,"label":"errDeserialize","id":195197,"variant":0,"Pos":""},{"rank":1.0416825539880061,"label":"Config","id":148564,"variant":0,"Pos":""},{"rank":1.0416825539880061,"label":"Notification","id":38748,"variant":0,"Pos":""},{"rank":1.1531668230239995,"label":"blockIndex","id":11694,"variant":0,"Pos":""},{"rank":6,"label":"chainView","id":81948,"variant":0,"Pos":""},{"rank":1.0416825539880061,"label":"medianTime","id":156512,"variant":0,"Pos":""},{"rank":1.0416825539880061,"label":"NotificationCallback","id":37281,"variant":0,"Pos":""},{"rank":2.4352359169379163,"label":"blockNode","id":5667,"variant":0,"Pos":""},{"rank":1.9335567062759489,"label":"thresholdStateCache","id":184480,"variant":0,"Pos":""},{"rank":1.0416825539880061,"label":"NotificationType","id":37138,"variant":0,"Pos":""},{"rank":1.0416825539880061,"label":"New","id":842533188656,"variant":2,"Pos":""},{"rank":1.0416825539880061,"label":"bestChainState","id":229867,"variant":0,"Pos":""}],"edges":[{"source":842533188656,"target":5667},{"source":842533188656,"target":5667},{"source":842533188656,"target":184480},{"source":842456547840,"target":243383},{"source":842533188656,"target":97978},{"source":842456547840,"target":194785},{"source":842456547840,"target":243383},{"source":842456547840,"target":243383},{"source":842533188656,"target":5667},{"source":842533188656,"target":81948},{"source":842533188656,"target":184480},{"source":842456547840,"target":247950},{"source":842533188656,"target":184480},{"source":842456547840,"target":243383},{"source":842456547840,"target":96166},{"source":842533188656,"target":97978},{"source":842533188656,"target":323005},{"source":842456547840,"target":70281},{"source":842533188656,"target":81948},{"source":842533188656,"target":184480},{"source":842533188656,"target":5667},{"source":842533188656,"target":184480},{"source":842533188656,"target":97978},{"source":842456547840,"target":243383},{"source":842533188656,"target":5667},{"source":842456547840,"target":243383},{"source":842456547840,"target":243383},{"source":842456547840,"target":247950},{"source":842456547840,"target":162176},{"source":842456547840,"target":162176},{"source":842456547840,"target":162176},{"source":842456547840,"target":243383},{"source":842456547840,"target":247950},{"source":842456547840,"target":243383},{"source":842456547840,"target":156512},{"source":842533188656,"target":5667},{"source":842533188656,"target":81948},{"source":842456547840,"target":195197},{"source":842456547840,"target":183402},{"source":842533188656,"target":184480},{"source":842456547840,"target":243383},{"source":842533188656,"target":184480},{"source":842533188656,"target":97978},{"source":842456547840,"target":155654},{"source":842456547840,"target":5667},{"source":842533188656,"target":81948},{"source":842456547840,"target":107421},{"source":842533188656,"target":81948},{"source":842456547840,"target":184480},{"source":842456547840,"target":162176},{"source":842456547840,"target":243383},{"source":842456547840,"target":69640},{"source":842533188656,"target":5667},{"source":842456547840,"target":243383},{"source":842456547840,"target":95965},{"source":842533188656,"target":5667},{"source":842456547840,"target":81948},{"source":842533188656,"target":97978},{"source":842533188656,"target":5667},{"source":842456547840,"target":243383},{"source":842456547840,"target":842533188656},{"source":842533188656,"target":97978},{"source":842456547840,"target":311978},{"source":842533188656,"target":5667},{"source":842456547840,"target":247950},{"source":842456547840,"target":148564},{"source":842456547840,"target":243383},{"source":842533188656,"target":81948},{"source":842456547840,"target":842533188672},{"source":842533188656,"target":842533187456},{"source":842533188656,"target":184480},{"source":842456547840,"target":162176},{"source":842533188656,"target":81948},{"source":842456547840,"target":200335},{"source":842456547840,"target":243383},{"source":842533188656,"target":81948},{"source":842456547840,"target":842533187232},{"source":842533188656,"target":184480},{"source":842456547840,"target":243383},{"source":842533188656,"target":81948},{"source":842533188656,"target":97978},{"source":842456547840,"target":242549},{"source":842533188656,"target":5667},{"source":842456547840,"target":162176},{"source":842533188656,"target":81948},{"source":842533188656,"target":11694},{"source":842456547840,"target":842533187456},{"source":842456547840,"target":247950},{"source":842533188656,"target":97978},{"source":842533188656,"target":5667},{"source":842533188656,"target":184480},{"source":842456547840,"target":229867},{"source":842456547840,"target":842533190176},{"source":842533188656,"target":81948},{"source":842456547840,"target":162176},{"source":842533188656,"target":5667},{"source":842533188656,"target":184480},{"source":842456547840,"target":247950},{"source":842456547840,"target":242549},{"source":842533188656,"target":184480},{"source":842456547840,"target":181526},{"source":842533188656,"target":5667},{"source":842456547840,"target":242549},{"source":842456547840,"target":162176},{"source":842456547840,"target":247950},{"source":842456547840,"target":3972},{"source":842456547840,"target":80122},{"source":842456547840,"target":242549},{"source":842533188656,"target":5667},{"source":842533188656,"target":97978},{"source":842456547840,"target":243383},{"source":842533188656,"target":184480},{"source":842456547840,"target":38748},{"source":842456547840,"target":243383},{"source":842456547840,"target":37281},{"source":842456547840,"target":162176},{"source":842456547840,"target":162176},{"source":842456547840,"target":97978},{"source":842533188656,"target":97978},{"source":842533188656,"target":5667},{"source":842533188656,"target":5667},{"source":842533188656,"target":184480},{"source":842456547840,"target":243383},{"source":842533188656,"target":5667},{"source":842456547840,"target":247950},{"source":842456547840,"target":61052},{"source":842456547840,"target":162176},{"source":842533188672,"target":81948},{"source":842533188656,"target":5667},{"source":842456547840,"target":243383},{"source":842456547840,"target":323005},{"source":842456547840,"target":242549},{"source":842456547840,"target":243383},{"source":842533188656,"target":5667},{"source":842456547840,"target":155041},{"source":842533188656,"target":5667},{"source":842456547840,"target":162176},{"source":842456547840,"target":96762},{"source":842533188656,"target":81948},{"source":842456547840,"target":243383},{"source":842533188656,"target":97978},{"source":842533188656,"target":5667},{"source":842456547840,"target":11694},{"source":842456547840,"target":242549},{"source":842533188656,"target":97978},{"source":842456547840,"target":147784},{"source":842533188656,"target":5667},{"source":842533188656,"target":81948},{"source":842533188656,"target":842533188672},{"source":842533188656,"target":97978},{"source":842533188656,"target":842533187232},{"source":842456547840,"target":242549},{"source":842456547840,"target":70031},{"source":842456547840,"target":162176},{"source":842456547840,"target":242549},{"source":842456547840,"target":243383},{"source":842533188656,"target":184480},{"source":842456547840,"target":37138},{"source":842456547840,"target":243383},{"source":842533188656,"target":184480},{"source":842456547840,"target":247950},{"source":842533188656,"target":11694},{"source":842533188656,"target":5667},{"source":842456547840,"target":162176},{"source":842456547840,"target":161838},{"source":842456547840,"target":243383},{"source":842456547840,"target":325922},{"source":842456547840,"target":243383},{"source":842533188656,"target":81948},{"source":842533188656,"target":5667},{"source":842456547840,"target":242549},{"source":842456547840,"target":162176},{"source":842456547840,"target":243383}],"nodeTypes":["Struct","Method","Func","Field","RootPackage","File","ImportedPackage","ImportedFunc","FuncCall"]}
